uP.v
//Jonathan Menéndez 18023
//Electrónica Digital - Proyecto 2
//uP nibbler de 4 bits


// FlipFlops tipo D para uso de Fetch, Flags, Outputs
module FFD1(
	input clk, reset, enable, d,
	output reg q);

	always@(posedge clk, posedge reset)
	if (reset) q <= 0;
	else if (enable) q <= d;
	else q <= q;
endmodule

module FFD2(
	input clk, reset, enable,
	input [1:0] d,
	output reg [1:0] q);

	always@(posedge clk, posedge reset)
		if (reset)
		  q <= 2'b0;
		else if (enable)
			q <= d;
		else
			q <= q;
endmodule

module FFD4(
	input clk, reset, enable,
  input [3:0] d,
	output reg [3:0] q);

	always@(posedge clk, posedge reset)
		if (reset)
			q <= 3'b0;
		else if (enable)
			q <= d;
		else
			q <= q;
endmodule

module FFD8(
	input clk, reset, enable,
	input [7:0] d,
	output reg [7:0] q);

	always@(posedge clk, posedge reset)
		if (reset)
			q <= 8'b0;
		else if (enable)
			q <= d;
  	else
			q <= q;
endmodule

 // FliFlop tipo T para el phase
module FFT (
  input clk, reset, enable,
  output q);

  wire d;
  assign d = ~q; // se niega el fetch para utilizarlo luego como enable

      FFD1 T(clk, reset, enable, d, q);

endmodule

 // Program Counter
module COUNTER (
	input clk, reset, enable, load, //inPC y loadPC
  input [0:11] data,      //12 bits de entrada y salida
  output reg [0:11] out);

  always @(posedge clk, posedge reset)
    if (~enable & ~load)
      out <= out;
    else if (reset)
      out <= 12'b0;
    else if (load)
      out <= data;
    else if (enable & ~load)
      out <= out + 12'b000000000001;

endmodule // contador

// Rom de instrucciones
module ROM (
  input [11:0] address,
  output [7:0] out); // parte de instr y oprnd que pasan al fetch

  reg [7:0] data [0:4095]; //numero de datos en la memoria

  initial begin
    $readmemh ("memory.list", data); //utiliza memoria con las instrucciones
  end
    assign out = data[address];

endmodule

// Buffer Tri-Estado para inputs y bus drivers
module BUFFTRI (
  input [3:0] a,
  input enable,
  output [3:0] y);  //para el data_bus

    assign y = enable ? a : 4'bz;

endmodule

// RAM
module RAM(
  input clk, we, cs,  //we = write enable ; cs = chip select
  input [11:0] address,
  input [3:0] in,
  output [3:0] out); // salida a un buffer

  reg [3:0] data [0:4095];

  always @ (posedge clk)
    if (cs & we) data[address] <= in;

  assign out = (cs&~we) ? data[address] : 4'bz;

endmodule

// Decoder
module DECODER (
  input wire [6:0] address,
  output reg [12:0] d);

  always @ ( address ) begin
    casex (address)  //casex para las instrucciones que van a la ALU
			//any
		7'bxxxxxx0: d <= 13'b1000000001000;
		  //JC = Jump if carry
    7'b00001x1: d <= 13'b0100000001000;
    7'b00000x1: d <= 13'b1000000001000;
			//JNC = Jump if not carry
    7'b00011x1: d <= 13'b1000000001000;
    7'b00010x1: d <= 13'b0100000001000;
			//CMP1
    7'b0010xx1: d <= 13'b0001001000010;
			//CMPM
    7'b0011xx1: d <= 13'b1001001100000;
			//LIT
    7'b0100xx1: d <= 13'b0011010000010;
			//IN
    7'b0101xx1: d <= 13'b0011010000100;
			//LD
    7'b0110xx1: d <= 13'b1011010100000;
			//ST
    7'b0111xx1: d <= 13'b1000000111000;
			//JZ
    7'b1000x11: d <= 13'b0100000001000;
    7'b1000x01: d <= 13'b1000000001000;
			//JNZ
    7'b1001x11: d <= 13'b1000000001000;
    7'b1001x01: d <= 13'b0100000001000;
			//ADDI
    7'b1010xx1: d <= 13'b0011011000010;
			//ADDM
    7'b1011xx1: d <= 13'b1011011100000;
			//JMP
    7'b1100xx1: d <= 13'b0100000001000;
			//OUT
    7'b1101xx1: d <= 13'b0000000001001;
			//NANDI
    7'b1110xx1: d <= 13'b0011100000010;
			//NANDM
    7'b1111xx1: d <= 13'b1011100100000;
    endcase
  end
endmodule

// ALU
module ALU (
  input reset,
  input [3:0] a, b,
  input [2:0] f,
  output reg [3:0] y,
  output reg c, zeta);

  parameter Pa = 3'b000; // se definen terminos para simplificar el case
  parameter Pb = 3'b010;
  parameter CMP = 3'b001;
  parameter ADD = 3'b011;
  parameter NOR = 3'b100;

  always @(*) begin
    c = 0;
		case(f)
      Pa: y = a;
      Pb: y = b;
      CMP: begin
            {c, y} = a-b; // necesario concatenar
           end
      ADD: begin
            {c, y} = a+b; // necesario concatenar
           end
      NOR: y = a~|b;
      default: y = 3'b0;
    endcase

  if (y == 0)
    zeta = 1;
  else
    zeta = 0;
  if (reset == 1)
    c = 0;
					  end
endmodule

// uP implementado con todos los módulos anteriores
module uP(
  input clock, reset, //entradas y salidas para el modulo completo
  input [3:0] pushbuttons,
  output phase, c_flag, z_flag,
  output [3:0] instr, oprnd, accu, data_bus, FF_out,
  output [7:0] program_byte,
  output [11:0] PC, address_RAM);


  wire [11:0] PC;  // Wire del nibbler y sus respectivos modulos
  wire enable_pc, load_pc;
  wire [7:0] program_byte;
  wire [3:0] instr, oprnd;
  wire we, cs;
	wire [3:0] data_bus;
  wire busA;
	wire [11:0] address_RAM;
	assign address_RAM = {oprnd, program_byte};
	wire [3:0] accu, res;
	wire enable_accu;
  wire [2:0] f;
  wire c, zeta;
  wire busB;
  wire enable_inputs;
	wire enable_outputs;
	wire phase;
	wire [1:0] flags;
  wire e_flags, c_flag, z_flag;
  assign c_flag = flags[1];
  assign z_flag = flags[0];
		//llamado a todos los modulos y su interconexion con los wires de arriba
  COUNTER counter(clock, reset, enable_pc, load_pc, address_RAM, PC);
  ROM rom(PC, program_byte);
  FFD8 fetch(clock, reset, ~phase, program_byte, {instr, oprnd});
	DECODER decoder({instr, flags, phase}, {enable_pc, load_pc, enable_accu, e_flags,
									f[2], f[1], f[0], cs, we, busB, enable_inputs, busA, enable_outputs});
  BUFFTRI FbusA(oprnd, busA, data_bus);
	RAM ram(clock, we, cs, address_RAM, data_bus, data_bus);
  FFD4 Faccu(clock, reset, enable_accu, res, accu);
  ALU alu(reset, accu, data_bus, f, res, c, zeta);
  BUFFTRI FbusB(res, busB, data_bus);
  BUFFTRI inputs(pushbuttons, enable_inputs, data_bus);
  FFD4 outputs(clock, reset, enable_outputs, data_bus, FF_out);
  FFT Fphase(clock, reset, 1'b1, phase);
  FFD2 Fflags(clock, reset, e_flags, {c, zeta}, flags);

endmodule

uP_tb.v
//Jonathan Menendez
// Electronica Digital - Proyecto 2
//uP_tb.v / nibbler de 4 bits

module testbench();
    reg clock, reset;       //salidas y entradas del uP
    reg [3:0] pushbuttons;
    wire phase, c_flag, z_flag;
    wire [3:0] instr, oprnd, accu, data_bus, FF_out;
    wire [7:0] program_byte;
    wire [11:0] PC, address_RAM;

    //llamado al modulo principal (uP) del proyectp
uP uP(.clock(clock),
      .reset(reset),
      .pushbuttons(pushbuttons),
      .phase(phase),
      .c_flag(c_flag),
      .z_flag(z_flag),
      .instr(instr),
      .oprnd(oprnd),
      .accu(accu),
      .data_bus(data_bus),
      .FF_out(FF_out),
      .program_byte(program_byte),
      .PC(PC),
      .address_RAM(address_RAM));

  initial
      #1000 $finish;    //tiempo donde finaliza la simulacion

  always
      #5 clock = ~clock;    //tiempo de cada flanco de reloj

    initial begin
      #1  //display sencillo del titulo y cada input y output en hexadecimal para hacerlo mas corto
      $display("\n");
      $display("Proyecto 2: uP Jonathan Menéndez");
      $display("\n");
      $display("| clk || rst || pushb || phase || c || z || instr || oprnd ||  accu || bus || FFo || pr_b ||   PC  || a_RAM |");
      $monitor("|  %h  ||  %h  ||   %h   ||   %h   || %h || %h ||   %h   ||   %h   ||   %h   ||  %h  ||  %h  ||  %h  ||  %h  ||  %h  |"
              ,clock, reset, pushbuttons, phase, c_flag, z_flag, instr, oprnd, accu, data_bus, FF_out, program_byte, PC, address_RAM);
      clock = 0; pushbuttons = 4'b0110; // valores iniciales y diferentes conbinaciones de los pushbuttons
      #2 reset = 1;
      #1 reset = 0;
      #200 pushbuttons = 4'b1001;
      #20 pushbuttons = 4'b0000;
      #20 pushbuttons = 4'b0001;
      #20 pushbuttons = 4'b0010;
      #20 pushbuttons = 4'b0011;
      #20 pushbuttons = 4'b0100;
      #20 pushbuttons = 4'b0101;
      #20 pushbuttons = 4'b0110;
      #20 pushbuttons = 4'b0111;
      #20 pushbuttons = 4'b1000;
      #20 pushbuttons = 4'b1001;
      #20 pushbuttons = 4'b1010;
      #20 pushbuttons = 4'b1011;
      #20 pushbuttons = 4'b1100;
      #20 pushbuttons = 4'b1101;
      #20 pushbuttons = 4'b1110;
      #20 pushbuttons = 4'b1111;

      end

      initial begin
          $dumpfile("uP_tb.vcd");  //llamado al GTKWave
          $dumpvars(0, testbench);
      end
  endmodule

uP_tb.vcd
$date
	Sun Nov 22 21:34:40 2020
$end
$version
	Icarus Verilog
$end
$timescale
	1ps
$end
$scope module testbench $end
$var wire 4 ! data_bus [3:0] $end
$var wire 1 " z_flag $end
$var wire 8 # program_byte [7:0] $end
$var wire 1 $ phase $end
$var wire 4 % oprnd [3:0] $end
$var wire 4 & instr [3:0] $end
$var wire 1 ' c_flag $end
$var wire 12 ( address_RAM [11:0] $end
$var wire 4 ) accu [3:0] $end
$var wire 12 * PC [11:0] $end
$var wire 4 + FF_out [3:0] $end
$var reg 1 , clock $end
$var reg 4 - pushbuttons [3:0] $end
$var reg 1 . reset $end
$scope module uP $end
$var wire 1 , clock $end
$var wire 4 / data_bus [3:0] $end
$var wire 4 0 pushbuttons [3:0] $end
$var wire 1 . reset $end
$var wire 1 1 zeta $end
$var wire 1 " z_flag $end
$var wire 1 2 we $end
$var wire 4 3 res [3:0] $end
$var wire 8 4 program_byte [7:0] $end
$var wire 1 $ phase $end
$var wire 4 5 oprnd [3:0] $end
$var wire 1 6 load_pc $end
$var wire 4 7 instr [3:0] $end
$var wire 2 8 flags [1:0] $end
$var wire 3 9 f [2:0] $end
$var wire 1 : enable_pc $end
$var wire 1 ; enable_outputs $end
$var wire 1 < enable_inputs $end
$var wire 1 = enable_accu $end
$var wire 1 > e_flags $end
$var wire 1 ? cs $end
$var wire 1 ' c_flag $end
$var wire 1 @ c $end
$var wire 1 A busB $end
$var wire 1 B busA $end
$var wire 12 C address_RAM [11:0] $end
$var wire 4 D accu [3:0] $end
$var wire 12 E PC [11:0] $end
$var wire 4 F FF_out [3:0] $end
$scope module Faccu $end
$var wire 1 , clk $end
$var wire 1 = enable $end
$var wire 1 . reset $end
$var wire 4 G d [3:0] $end
$var reg 4 H q [3:0] $end
$upscope $end
$scope module FbusA $end
$var wire 4 I a [3:0] $end
$var wire 1 B enable $end
$var wire 4 J y [3:0] $end
$upscope $end
$scope module FbusB $end
$var wire 1 A enable $end
$var wire 4 K y [3:0] $end
$var wire 4 L a [3:0] $end
$upscope $end
$scope module Fflags $end
$var wire 1 , clk $end
$var wire 2 M d [1:0] $end
$var wire 1 > enable $end
$var wire 1 . reset $end
$var reg 2 N q [1:0] $end
$upscope $end
$scope module Fphase $end
$var wire 1 , clk $end
$var wire 1 O d $end
$var wire 1 P enable $end
$var wire 1 . reset $end
$var wire 1 $ q $end
$scope module T $end
$var wire 1 , clk $end
$var wire 1 O d $end
$var wire 1 P enable $end
$var wire 1 . reset $end
$var reg 1 $ q $end
$upscope $end
$upscope $end
$scope module alu $end
$var wire 4 Q a [3:0] $end
$var wire 4 R b [3:0] $end
$var wire 3 S f [2:0] $end
$var wire 1 . reset $end
$var reg 1 @ c $end
$var reg 4 T y [3:0] $end
$var reg 1 1 zeta $end
$upscope $end
$scope module counter $end
$var wire 1 , clk $end
$var wire 12 U data [0:11] $end
$var wire 1 : enable $end
$var wire 1 6 load $end
$var wire 1 . reset $end
$var reg 12 V out [0:11] $end
$upscope $end
$scope module decoder $end
$var wire 7 W address [6:0] $end
$var reg 13 X d [12:0] $end
$upscope $end
$scope module fetch $end
$var wire 1 , clk $end
$var wire 1 Y enable $end
$var wire 1 . reset $end
$var wire 8 Z d [7:0] $end
$var reg 8 [ q [7:0] $end
$upscope $end
$scope module inputs $end
$var wire 4 \ a [3:0] $end
$var wire 1 < enable $end
$var wire 4 ] y [3:0] $end
$upscope $end
$scope module outputs $end
$var wire 1 , clk $end
$var wire 4 ^ d [3:0] $end
$var wire 1 ; enable $end
$var wire 1 . reset $end
$var reg 4 _ q [3:0] $end
$upscope $end
$scope module ram $end
$var wire 12 ` address [11:0] $end
$var wire 1 , clk $end
$var wire 1 ? cs $end
$var wire 4 a in [3:0] $end
$var wire 4 b out [3:0] $end
$var wire 1 2 we $end
$upscope $end
$scope module rom $end
$var wire 12 c address [11:0] $end
$var wire 8 d out [7:0] $end
$upscope $end
$upscope $end
$upscope $end
$enddefinitions $end
#0
$dumpvars
bx d
bx c
bx b
bx a
bx `
bx _
bx ^
bx ]
bx \
bx [
bx Z
xY
bx X
bx W
bx V
bx U
bx T
bx S
bx R
bx Q
1P
xO
bx N
bx M
bx L
bx K
bx J
bx I
bx H
bx G
bx F
bx E
bx D
bx C
xB
xA
x@
x?
x>
x=
x<
x;
x:
bx 9
bx 8
bx 7
x6
bx 5
bx 4
bx 3
x2
x1
bx 0
bx /
x.
bx -
x,
bx +
bx *
bx )
bx (
x'
bx &
bx %
x$
bx #
x"
bx !
$end
#1
b110 -
b110 0
b110 \
0,
#3
b0 !
b0 /
b0 J
b0 K
b0 R
b0 ]
b0 ^
b0 a
b0 b
0;
0B
0<
1A
02
0?
b0 9
b0 S
0>
0=
06
1:
b1000000001000 X
b0 %
b0 5
b0 I
b0 &
b0 7
1O
1Y
0"
0'
b1001001 (
b1001001 C
b1001001 U
b1001001 `
b1001001 #
b1001001 4
b1001001 Z
b1001001 d
b0 *
b0 E
b0 V
b0 c
b0 [
b0 )
b0 D
b0 H
b0 Q
b0 +
b0 F
b0 _
0$
b0 W
b0 8
b0 N
11
b0 3
b0 G
b0 L
b0 T
b1 M
0@
1.
#4
0.
#5
b0 M
01
b1001 3
b1001 G
b1001 L
b1001 T
b1001 !
b1001 /
b1001 J
b1001 K
b1001 R
b1001 ]
b1001 ^
b1001 a
b1001 b
1B
0A
b10 9
b10 S
1>
1=
0:
b11010000010 X
0O
0Y
b1001 %
b1001 5
b1001 I
b100 &
b100 7
b100001 W
1$
b1001001 [
b100101010000 (
b100101010000 C
b100101010000 U
b100101010000 `
b1010000 #
b1010000 4
b1010000 Z
b1010000 d
b1 *
b1 E
b1 V
b1 c
1,
#10
0,
#15
0B
1A
b0 9
b0 S
0>
0=
1:
b1000000001000 X
1O
1Y
b1001 )
b1001 D
b1001 H
b1001 Q
b100000 W
0$
1,
#20
0,
#25
b110 3
b110 G
b110 L
b110 T
b110 !
b110 /
b110 J
b110 K
b110 R
b110 ]
b110 ^
b110 a
b110 b
1<
0A
b10 9
b10 S
1>
1=
0:
b11010000100 X
0O
0Y
b0 %
b0 5
b0 I
b101 &
b101 7
b101001 W
1$
b1010000 [
b1001111 (
b1001111 C
b1001111 U
b1001111 `
b1001111 #
b1001111 4
b1001111 Z
b1001111 d
b10 *
b10 E
b10 V
b10 c
1,
#30
0,
#35
0<
1A
b0 9
b0 S
0>
0=
1:
b1000000001000 X
1O
1Y
b110 )
b110 D
b110 H
b110 Q
b101000 W
0$
1,
#40
0,
#45
b1111 3
b1111 G
b1111 L
b1111 T
b1111 !
b1111 /
b1111 J
b1111 K
b1111 R
b1111 ]
b1111 ^
b1111 a
b1111 b
1B
0A
b10 9
b10 S
1>
1=
0:
b11010000010 X
0O
0Y
b1111 %
b1111 5
b1111 I
b100 &
b100 7
b100001 W
1$
b1001111 [
b111110100001 (
b111110100001 C
b111110100001 U
b111110100001 `
b10100001 #
b10100001 4
b10100001 Z
b10100001 d
b11 *
b11 E
b11 V
b11 c
1,
#50
0,
#55
0B
1A
b0 9
b0 S
0>
0=
1:
b1000000001000 X
1O
1Y
b1111 )
b1111 D
b1111 H
b1111 Q
b100000 W
0$
1,
#60
0,
#65
11
b1 !
b1 /
b1 J
b1 K
b1 R
b1 ]
b1 ^
b1 a
b1 b
b11 M
1@
b0 3
b0 G
b0 L
b0 T
1B
0A
b11 9
b11 S
1>
1=
0:
b11011000010 X
0O
0Y
b1 %
b1 5
b1 I
b1010 &
b1010 7
b1010001 W
1$
b10100001 [
b101000101 (
b101000101 C
b101000101 U
b101000101 `
b1000101 #
b1000101 4
b1000101 Z
b1000101 d
b100 *
b100 E
b100 V
b100 c
1,
#70
0,
#75
b0 !
b0 /
b0 J
b0 K
b0 R
b0 ]
b0 ^
b0 a
b0 b
0B
1A
b0 9
b0 S
0>
0=
1:
b1000000001000 X
11
b0 3
b0 G
b0 L
b0 T
b1 M
0@
1O
1Y
1"
1'
b0 )
b0 D
b0 H
b0 Q
0$
b1010110 W
b11 8
b11 N
1,
#80
0,
#85
b0 M
01
b101 3
b101 G
b101 L
b101 T
b101 !
b101 /
b101 J
b101 K
b101 R
b101 ]
b101 ^
b101 a
b101 b
1B
0A
b10 9
b10 S
1>
1=
0:
b11010000010 X
0O
0Y
b101 %
b101 5
b101 I
b100 &
b100 7
b100111 W
1$
b1000101 [
b10101110000 (
b10101110000 C
b10101110000 U
b10101110000 `
b1110000 #
b1110000 4
b1110000 Z
b1110000 d
b101 *
b101 E
b101 V
b101 c
1,
#90
0,
#95
0B
1A
b0 9
b0 S
0>
0=
1:
b1000000001000 X
1O
1Y
0"
0'
b101 )
b101 D
b101 H
b101 Q
0$
b100000 W
b0 8
b0 N
1,
#100
0,
#105
b101 !
b101 /
b101 J
b101 K
b101 R
b101 ]
b101 ^
b101 a
b101 b
12
1?
b1000000111000 X
0O
0Y
b0 %
b0 5
b0 I
b111 &
b111 7
b111001 W
1$
b1110000 [
b100010 (
b100010 C
b100010 U
b100010 `
b100010 #
b100010 4
b100010 Z
b100010 d
b110 *
b110 E
b110 V
b110 c
1,
#110
0,
#115
02
0?
b1000000001000 X
1O
1Y
b1000001 (
b1000001 C
b1000001 U
b1000001 `
b1000001 #
b1000001 4
b1000001 Z
b1000001 d
b111 *
b111 E
b111 V
b111 c
b111000 W
0$
1,
#120
0,
#125
b1 3
b1 G
b1 L
b1 T
b1 !
b1 /
b1 J
b1 K
b1 R
b1 ]
b1 ^
b1 a
b1 b
1B
0A
b10 9
b10 S
1>
1=
0:
b11010000010 X
0O
0Y
b1 %
b1 5
b1 I
b100 &
b100 7
b100001 W
1$
b1000001 [
b101110000 (
b101110000 C
b101110000 U
b101110000 `
b1110000 #
b1110000 4
b1110000 Z
b1110000 d
b1000 *
b1000 E
b1000 V
b1000 c
1,
#130
0,
#135
0B
1A
b0 9
b0 S
0>
0=
1:
b1000000001000 X
1O
1Y
b1 )
b1 D
b1 H
b1 Q
b100000 W
0$
1,
#140
0,
#145
b1 !
b1 /
b1 J
b1 K
b1 R
b1 ]
b1 ^
b1 a
b1 b
12
1?
b1000000111000 X
0O
0Y
b0 %
b0 5
b0 I
b111 &
b111 7
b111001 W
1$
b1110000 [
b100010 (
b100010 C
b100010 U
b100010 `
b100010 #
b100010 4
b100010 Z
b100010 d
b1001 *
b1001 E
b1001 V
b1001 c
1,
#150
0,
#155
02
0?
b1000000001000 X
1O
1Y
b1001110 (
b1001110 C
b1001110 U
b1001110 `
b1001110 #
b1001110 4
b1001110 Z
b1001110 d
b1010 *
b1010 E
b1010 V
b1010 c
b111000 W
0$
1,
#160
0,
#165
b1110 3
b1110 G
b1110 L
b1110 T
b1110 !
b1110 /
b1110 J
b1110 K
b1110 R
b1110 ]
b1110 ^
b1110 a
b1110 b
1B
0A
b10 9
b10 S
1>
1=
0:
b11010000010 X
0O
0Y
b1110 %
b1110 5
b1110 I
b100 &
b100 7
b100001 W
1$
b1001110 [
b111001110000 (
b111001110000 C
b111001110000 U
b111001110000 `
b1110000 #
b1110000 4
b1110000 Z
b1110000 d
b1011 *
b1011 E
b1011 V
b1011 c
1,
#170
0,
#175
0B
1A
b0 9
b0 S
0>
0=
1:
b1000000001000 X
1O
1Y
b1110 )
b1110 D
b1110 H
b1110 Q
b100000 W
0$
1,
#180
0,
#185
b1110 !
b1110 /
b1110 J
b1110 K
b1110 R
b1110 ]
b1110 ^
b1110 a
b1110 b
12
1?
b1000000111000 X
0O
0Y
b0 %
b0 5
b0 I
b111 &
b111 7
b111001 W
1$
b1110000 [
b0 (
b0 C
b0 U
b0 `
b0 #
b0 4
b0 Z
b0 d
b1100 *
b1100 E
b1100 V
b1100 c
1,
#190
0,
#195
02
0?
b1000000001000 X
1O
1Y
b1000000 (
b1000000 C
b1000000 U
b1000000 `
b1000000 #
b1000000 4
b1000000 Z
b1000000 d
b1101 *
b1101 E
b1101 V
b1101 c
b111000 W
0$
1,
#200
0,
#204
b1001 -
b1001 0
b1001 \
#205
b1 M
11
b0 3
b0 G
b0 L
b0 T
b0 !
b0 /
b0 J
b0 K
b0 R
b0 ]
b0 ^
b0 a
b0 b
1B
0A
b10 9
b10 S
1>
1=
0:
b11010000010 X
0O
0Y
b100 &
b100 7
b100001 W
1$
b1000000 [
b1100000 (
b1100000 C
b1100000 U
b1100000 `
b1100000 #
b1100000 4
b1100000 Z
b1100000 d
b1110 *
b1110 E
b1110 V
b1110 c
1,
#210
0,
#215
0B
1A
b0 9
b0 S
0>
0=
1:
b1000000001000 X
1O
1Y
1"
b0 )
b0 D
b0 H
b0 Q
0$
b100010 W
b1 8
b1 N
1,
#220
0,
#224
b0 -
b0 0
b0 \
#225
b0 M
01
b1110 3
b1110 G
b1110 L
b1110 T
b1110 !
b1110 /
b1110 J
b1110 K
b1110 R
b1110 ]
b1110 ^
b1110 a
b1110 b
0A
1?
b10 9
b10 S
1>
1=
b1011010100000 X
0O
0Y
b110 &
b110 7
b110011 W
1$
b1100000 [
b0 (
b0 C
b0 U
b0 `
b0 #
b0 4
b0 Z
b0 d
b1111 *
b1111 E
b1111 V
b1111 c
1,
#230
0,
#235
1A
0?
b0 9
b0 S
0>
0=
b1000000001000 X
b1110 3
b1110 G
b1110 L
b1110 T
b1110 !
b1110 /
b1110 J
b1110 K
b1110 R
b1110 ]
b1110 ^
b1110 a
b1110 b
1O
1Y
0"
b1000010 (
b1000010 C
b1000010 U
b1000010 `
b1000010 #
b1000010 4
b1000010 Z
b1000010 d
b10000 *
b10000 E
b10000 V
b10000 c
b1110 )
b1110 D
b1110 H
b1110 Q
0$
b110000 W
b0 8
b0 N
1,
#240
0,
#244
b1 -
b1 0
b1 \
#245
b10 3
b10 G
b10 L
b10 T
b10 !
b10 /
b10 J
b10 K
b10 R
b10 ]
b10 ^
b10 a
b10 b
1B
0A
b10 9
b10 S
1>
1=
0:
b11010000010 X
0O
0Y
b10 %
b10 5
b10 I
b100 &
b100 7
b100001 W
1$
b1000010 [
b1010110000 (
b1010110000 C
b1010110000 U
b1010110000 `
b10110000 #
b10110000 4
b10110000 Z
b10110000 d
b10001 *
b10001 E
b10001 V
b10001 c
1,
#250
0,
#255
0B
1A
b0 9
b0 S
0>
0=
1:
b1000000001000 X
1O
1Y
b10 )
b10 D
b10 H
b10 Q
b100000 W
0$
1,
#260
0,
#264
b10 -
b10 0
b10 \
#265
11
b11 M
1@
b1110 !
b1110 /
b1110 J
b1110 K
b1110 R
b1110 ]
b1110 ^
b1110 a
b1110 b
b0 3
b0 G
b0 L
b0 T
0A
1?
b11 9
b11 S
1>
1=
b1011011100000 X
0O
0Y
b0 %
b0 5
b0 I
b1011 &
b1011 7
b1011001 W
1$
b10110000 [
b0 (
b0 C
b0 U
b0 `
b0 #
b0 4
b0 Z
b0 d
b10010 *
b10010 E
b10010 V
b10010 c
1,
#270
0,
#275
1A
0?
b0 9
b0 S
0>
0=
b1000000001000 X
b0 !
b0 /
b0 J
b0 K
b0 R
b0 ]
b0 ^
b0 a
b0 b
11
b0 3
b0 G
b0 L
b0 T
b1 M
0@
1O
1Y
1"
1'
b1000110 (
b1000110 C
b1000110 U
b1000110 `
b1000110 #
b1000110 4
b1000110 Z
b1000110 d
b10011 *
b10011 E
b10011 V
b10011 c
b0 )
b0 D
b0 H
b0 Q
0$
b1011110 W
b11 8
b11 N
1,
#280
0,
#284
b11 -
b11 0
b11 \
#285
b0 M
01
b110 3
b110 G
b110 L
b110 T
b110 !
b110 /
b110 J
b110 K
b110 R
b110 ]
b110 ^
b110 a
b110 b
1B
0A
b10 9
b10 S
1>
1=
0:
b11010000010 X
0O
0Y
b110 %
b110 5
b110 I
b100 &
b100 7
b100111 W
1$
b1000110 [
b11011110010 (
b11011110010 C
b11011110010 U
b11011110010 `
b11110010 #
b11110010 4
b11110010 Z
b11110010 d
b10100 *
b10100 E
b10100 V
b10100 c
1,
#290
0,
#295
0B
1A
b0 9
b0 S
0>
0=
1:
b1000000001000 X
1O
1Y
0"
0'
b110 )
b110 D
b110 H
b110 Q
0$
b100000 W
b0 8
b0 N
1,
#300
0,
#304
b100 -
b100 0
b100 \
#305
bx !
bx /
bx J
bx K
bx R
bx ]
bx ^
bx a
bx b
bx00x 3
bx00x G
bx00x L
bx00x T
0A
1?
b100 9
b100 S
1>
1=
b1011100100000 X
0O
0Y
b10 %
b10 5
b10 I
b1111 &
b1111 7
b1111001 W
1$
b11110010 [
b1000000000 (
b1000000000 C
b1000000000 U
b1000000000 `
b0 #
b0 4
b0 Z
b0 d
b10101 *
b10101 E
b10101 V
b10101 c
1,
#310
0,
#315
bx00x !
bx00x /
bx00x J
bx00x K
bx00x R
bx00x ]
bx00x ^
bx00x a
bx00x b
1A
0?
b0 9
b0 S
0>
0=
b1000000001000 X
bx00x 3
bx00x G
bx00x L
bx00x T
1O
1Y
b1001001111 (
b1001001111 C
b1001001111 U
b1001001111 `
b1001111 #
b1001111 4
b1001111 Z
b1001111 d
b10110 *
b10110 E
b10110 V
b10110 c
bx00x )
bx00x D
bx00x H
bx00x Q
b1111000 W
0$
1,
#320
0,
#324
b101 -
b101 0
b101 \
#325
b1111 3
b1111 G
b1111 L
b1111 T
b1111 !
b1111 /
b1111 J
b1111 K
b1111 R
b1111 ]
b1111 ^
b1111 a
b1111 b
1B
0A
b10 9
b10 S
1>
1=
0:
b11010000010 X
0O
0Y
b1111 %
b1111 5
b1111 I
b100 &
b100 7
b100001 W
1$
b1001111 [
b111110100001 (
b111110100001 C
b111110100001 U
b111110100001 `
b10100001 #
b10100001 4
b10100001 Z
b10100001 d
b10111 *
b10111 E
b10111 V
b10111 c
1,
#330
0,
#335
0B
1A
b0 9
b0 S
0>
0=
1:
b1000000001000 X
1O
1Y
b1111 )
b1111 D
b1111 H
b1111 Q
b100000 W
0$
1,
#340
0,
#344
b110 -
b110 0
b110 \
#345
11
b1 !
b1 /
b1 J
b1 K
b1 R
b1 ]
b1 ^
b1 a
b1 b
b11 M
1@
b0 3
b0 G
b0 L
b0 T
1B
0A
b11 9
b11 S
1>
1=
0:
b11011000010 X
0O
0Y
b1 %
b1 5
b1 I
b1010 &
b1010 7
b1010001 W
1$
b10100001 [
b101001111 (
b101001111 C
b101001111 U
b101001111 `
b1001111 #
b1001111 4
b1001111 Z
b1001111 d
b11000 *
b11000 E
b11000 V
b11000 c
1,
#350
0,
#355
b0 !
b0 /
b0 J
b0 K
b0 R
b0 ]
b0 ^
b0 a
b0 b
0B
1A
b0 9
b0 S
0>
0=
1:
b1000000001000 X
11
b0 3
b0 G
b0 L
b0 T
b1 M
0@
1O
1Y
1"
1'
b0 )
b0 D
b0 H
b0 Q
0$
b1010110 W
b11 8
b11 N
1,
#360
0,
#364
b111 -
b111 0
b111 \
#365
b0 M
01
b1111 3
b1111 G
b1111 L
b1111 T
b1111 !
b1111 /
b1111 J
b1111 K
b1111 R
b1111 ]
b1111 ^
b1111 a
b1111 b
1B
0A
b10 9
b10 S
1>
1=
0:
b11010000010 X
0O
0Y
b1111 %
b1111 5
b1111 I
b100 &
b100 7
b100111 W
1$
b1001111 [
b111110001111 (
b111110001111 C
b111110001111 U
b111110001111 `
b10001111 #
b10001111 4
b10001111 Z
b10001111 d
b11001 *
b11001 E
b11001 V
b11001 c
1,
#370
0,
#375
0B
1A
b0 9
b0 S
0>
0=
1:
b1000000001000 X
1O
1Y
0"
0'
b1111 )
b1111 D
b1111 H
b1111 Q
0$
b100000 W
b0 8
b0 N
1,
#380
0,
#384
b1000 -
b1000 0
b1000 \
#385
0O
0Y
b1000 &
b1000 7
b1000001 W
1$
b10001111 [
b111100000000 (
b111100000000 C
b111100000000 U
b111100000000 `
b0 #
b0 4
b0 Z
b0 d
b11010 *
b11010 E
b11010 V
b11010 c
1,
#390
0,
#395
1O
1Y
b111101000000 (
b111101000000 C
b111101000000 U
b111101000000 `
b1000000 #
b1000000 4
b1000000 Z
b1000000 d
b11011 *
b11011 E
b11011 V
b11011 c
b1000000 W
0$
1,
#400
0,
#404
b1001 -
b1001 0
b1001 \
#405
b1 M
11
b0 3
b0 G
b0 L
b0 T
b0 !
b0 /
b0 J
b0 K
b0 R
b0 ]
b0 ^
b0 a
b0 b
1B
0A
b10 9
b10 S
1>
1=
0:
b11010000010 X
0O
0Y
b0 %
b0 5
b0 I
b100 &
b100 7
b100001 W
1$
b1000000 [
b11101011 (
b11101011 C
b11101011 U
b11101011 `
b11101011 #
b11101011 4
b11101011 Z
b11101011 d
b11100 *
b11100 E
b11100 V
b11100 c
1,
#410
0,
#415
0B
1A
b0 9
b0 S
0>
0=
1:
b1000000001000 X
1O
1Y
1"
b0 )
b0 D
b0 H
b0 Q
0$
b100010 W
b1 8
b1 N
1,
#420
0,
#424
b1010 -
b1010 0
b1010 \
#425
b1011 !
b1011 /
b1011 J
b1011 K
b1011 R
b1011 ]
b1011 ^
b1011 a
b1011 b
b0 M
01
b100 3
b100 G
b100 L
b100 T
1B
0A
b100 9
b100 S
1>
1=
0:
b11100000010 X
0O
0Y
b1011 %
b1011 5
b1011 I
b1110 &
b1110 7
b1110011 W
1$
b11101011 [
b101111000000 (
b101111000000 C
b101111000000 U
b101111000000 `
b11000000 #
b11000000 4
b11000000 Z
b11000000 d
b11101 *
b11101 E
b11101 V
b11101 c
1,
#430
0,
